copick_utils/__init__.py
copick_utils/cli/__init__.py
copick_utils/cli/clipmesh.py
copick_utils/cli/clippicks.py
copick_utils/cli/clipseg.py
copick_utils/cli/conversion_commands.py
copick_utils/cli/enclosed.py
copick_utils/cli/filter_components.py
copick_utils/cli/fit_spline.py
copick_utils/cli/hull.py
copick_utils/cli/input_output_selection.py
copick_utils/cli/logical_commands.py
copick_utils/cli/mesh2picks.py
copick_utils/cli/mesh2seg.py
copick_utils/cli/meshop.py
copick_utils/cli/picks2ellipsoid.py
copick_utils/cli/picks2mesh.py
copick_utils/cli/picks2plane.py
copick_utils/cli/picks2seg.py
copick_utils/cli/picks2sphere.py
copick_utils/cli/picks2surface.py
copick_utils/cli/picksin.py
copick_utils/cli/picksout.py
copick_utils/cli/processing_commands.py
copick_utils/cli/seg2mesh.py
copick_utils/cli/seg2picks.py
copick_utils/cli/segop.py
copick_utils/cli/separate_components.py
copick_utils/cli/skeletonize.py
copick_utils/cli/split_labels.py
copick_utils/cli/util.py
copick_utils/cli/validbox.py
copick_utils/converters/__init__.py
copick_utils/converters/converter_common.py
copick_utils/converters/ellipsoid_from_picks.py
copick_utils/converters/lazy_converter.py
copick_utils/converters/mesh_from_picks.py
copick_utils/converters/mesh_from_segmentation.py
copick_utils/converters/picks_from_mesh.py
copick_utils/converters/picks_from_segmentation.py
copick_utils/converters/plane_from_picks.py
copick_utils/converters/segmentation_from_mesh.py
copick_utils/converters/segmentation_from_picks.py
copick_utils/converters/sphere_from_picks.py
copick_utils/converters/surface_from_picks.py
copick_utils/features/__init__.py
copick_utils/features/skimage.py
copick_utils/io/__init__.py
copick_utils/io/readers.py
copick_utils/io/writers.py
copick_utils/logical/__init__.py
copick_utils/logical/distance_operations.py
copick_utils/logical/enclosed_operations.py
copick_utils/logical/mesh_operations.py
copick_utils/logical/point_operations.py
copick_utils/logical/segmentation_operations.py
copick_utils-1.1.0.dist-info/METADATA
copick_utils-1.1.0.dist-info/WHEEL
copick_utils-1.1.0.dist-info/entry_points.txt
copick_utils-1.1.0.dist-info/licenses/LICENSE
copick_utils-1.1.0.dist-info/RECORD
