Metadata-Version: 2.4
Name: copick-utils
Version: 1.1.0
Summary: Utilities for copick
Project-URL: Repository, https://github.com/KyleHarrington/copick-utils.git
Project-URL: Issues, https://github.com/KyleHarrington/copick-utils/issues
Project-URL: Documentation, https://github.com/KyleHarrington/copick-utils#readme
Author-email: Kyle Harrington <czi@kyleharrington.com>, Jonathan Schwartz <jonathan.schwartz@czii.org>
License: MIT License
License-File: LICENSE
Keywords: annotation,copick,cryo-et,cryoet,tomography,utilities
Classifier: Development Status :: 4 - Beta
Classifier: License :: OSI Approved :: MIT License
Classifier: Programming Language :: Python
Classifier: Programming Language :: Python :: 3.9
Classifier: Programming Language :: Python :: 3.10
Classifier: Programming Language :: Python :: 3.11
Classifier: Programming Language :: Python :: 3.12
Classifier: Programming Language :: Python :: 3.13
Classifier: Programming Language :: Python :: Implementation :: CPython
Classifier: Programming Language :: Python :: Implementation :: PyPy
Requires-Python: >=3.9
Requires-Dist: click
Requires-Dist: click-option-group
Requires-Dist: copick>=1.16.0
Requires-Dist: manifold3d
Requires-Dist: mapbox-earcut
Requires-Dist: numpy
Requires-Dist: rtree
Requires-Dist: scikit-image
Requires-Dist: scikit-learn
Requires-Dist: scipy
Requires-Dist: shapely
Requires-Dist: tqdm
Requires-Dist: trimesh
Requires-Dist: zarr
Provides-Extra: dev
Requires-Dist: black>=25.1.0; extra == 'dev'
Requires-Dist: hatch-vcs>=0.4.0; extra == 'dev'
Requires-Dist: hatchling>=1.25.0; extra == 'dev'
Requires-Dist: pre-commit>=4.2.0; extra == 'dev'
Requires-Dist: ruff>=0.12.0; extra == 'dev'
